Tabla 02_SOP/Tabla02_SOP.v
//Nicole Prem 18337
module SOP_02 ();

wire out1, out2, out3, out4, out5, out6, out7;
reg A, B, C;

not NotA (out1, A); //compuertas not
not NotB (out2, B);
not NotC (out3, C);

and And1(out4, out1, out2, C);
and And2(out5, A, B, out3);
and And3(out6, A, B, C);

or Or1(out7, out4, out5, out6);

initial begin

$monitor("Time%d: A=%b B=%b C=%b out1=%b out2=%b out3=%b out4=%b out5=%b out6=%b out7=%b");

A=0; B=0; C=0; //1

#1 C=1; //2
#1 B=1; C=0; //3
#1 C=1; //4
#1 A=1; B=0; C=0; //5
#1 C=1; //6
#1 C=0; B=1; //7
#1 C=1; //8
#1 $finish;

end

initial
        begin
            $dumpfile("Tabla02_SOP_tb.vcd"); 
            $dumpvars(0, SOP_02); 
        end

endmodule

Tabla 02_SOP/Tabla02_SOP_tb.vcd
$date
	Fri Jul 31 21:49:18 2020
$end
$version
	Icarus Verilog
$end
$timescale
	1ps
$end
$scope module SOP_02 $end
$var wire 1 ! out1 $end
$var wire 1 " out2 $end
$var wire 1 # out3 $end
$var wire 1 $ out4 $end
$var wire 1 % out5 $end
$var wire 1 & out6 $end
$var wire 1 ' out7 $end
$var reg 1 ( A $end
$var reg 1 ) B $end
$var reg 1 * C $end
$upscope $end
$enddefinitions $end
#0
$dumpvars
0*
0)
0(
0'
0&
0%
0$
1#
1"
1!
$end
#1
1'
1$
0#
1*
#2
0'
0$
1#
0"
0*
1)
#3
0#
1*
#4
1#
1"
0!
0*
0)
1(
#5
0#
1*
#6
1'
1%
0"
1#
1)
0*
#7
0%
1&
0#
1*
